mini/__init__.py
mini/mini_sdk.py
mini/pkg_tool.py
mini/apis/__init__.py
mini/apis/api_action.py
mini/apis/api_behavior.py
mini/apis/api_config.py
mini/apis/api_content.py
mini/apis/api_expression.py
mini/apis/api_observe.py
mini/apis/api_sence.py
mini/apis/api_setup.py
mini/apis/api_sound.py
mini/apis/base_api.py
mini/apis/cmdid.py
mini/apis/errors.py
mini/channels/__init__.py
mini/channels/msg_utils.py
mini/channels/websocket_client.py
mini/channels/websocket_server.py
mini/dns/__init__.py
mini/dns/dns_browser.py
mini/dns/zeroconf.py
mini/pb2/__init__.py
mini/pb2/blebindorswitchwifi_pb2.py
mini/pb2/bthandshake_pb2.py
mini/pb2/cloudstorageurls_pb2.py
mini/pb2/cloudtranslate_pb2.py
mini/pb2/cloudwiki_pb2.py
mini/pb2/cmprivacymode_pb2.py
mini/pb2/codemao_actioninfo_pb2.py
mini/pb2/codemao_changerobotvolume_pb2.py
mini/pb2/codemao_controlbehavior_pb2.py
mini/pb2/codemao_controlfindface_pb2.py
mini/pb2/codemao_controlmouthlamp_pb2.py
mini/pb2/codemao_controlregisterface_pb2.py
mini/pb2/codemao_controlrobotrecord_pb2.py
mini/pb2/codemao_controlrunningprogram_pb2.py
mini/pb2/codemao_controltts_pb2.py
mini/pb2/codemao_expressioninfo_pb2.py
mini/pb2/codemao_faceanalyze_pb2.py
mini/pb2/codemao_facedetect_pb2.py
mini/pb2/codemao_facedetecttask_pb2.py
mini/pb2/codemao_faceinfo_pb2.py
mini/pb2/codemao_facerecognise_pb2.py
mini/pb2/codemao_facerecognisetask_pb2.py
mini/pb2/codemao_getactionlist_pb2.py
mini/pb2/codemao_getaudiolist_pb2.py
mini/pb2/codemao_getinfrareddistance_pb2.py
mini/pb2/codemao_getregisterfaces_pb2.py
mini/pb2/codemao_getrobotexpression_pb2.py
mini/pb2/codemao_getrobotsid_pb2.py
mini/pb2/codemao_getserverinfo_pb2.py
mini/pb2/codemao_handshake_pb2.py
mini/pb2/codemao_moverobot_pb2.py
mini/pb2/codemao_observebutterystatus_pb2.py
mini/pb2/codemao_observefallclimb_pb2.py
mini/pb2/codemao_observeheadracket_pb2.py
mini/pb2/codemao_observeinfrareddistance_pb2.py
mini/pb2/codemao_observevolumekeypress_pb2.py
mini/pb2/codemao_playaction_pb2.py
alphamini-1.2.0.dist-info/LICENSE
alphamini-1.2.0.dist-info/METADATA
alphamini-1.2.0.dist-info/WHEEL
alphamini-1.2.0.dist-info/entry_points.txt
alphamini-1.2.0.dist-info/top_level.txt
alphamini-1.2.0.dist-info/RECORD
