Metadata-Version: 2.1
Name: alphamini
Version: 1.2.0
Summary: python sdk for ubtech alpha mini robot
Home-page: UNKNOWN
Author: logic.peng
Author-email: logic.peng@ubtrobot.com
License: GPLv3
Platform: UNKNOWN
Classifier: Programming Language :: Python :: 3
Classifier: License :: OSI Approved :: MIT License
Classifier: Operating System :: OS Independent
Requires-Python: >=3.7
License-File: LICENSE
